MANIFEST.in
README.rst
setup.py
MeuProjeto1.egg-info/PKG-INFO
MeuProjeto1.egg-info/SOURCES.txt
MeuProjeto1.egg-info/dependency_links.txt
MeuProjeto1.egg-info/top_level.txt
MeusModulos/__init__.py
MeusModulos/some_module.py
MeusModulos/bar/__init__.py
MeusModulos/bar/my_package2.py
MeusModulos/foo/__init__.py
MeusModulos/foo/my_package3.py