Metadata-Version: 1.0
Name: MeuProjeto1
Version: 0.4
Summary: Example package that calculate thermodynamic data
Home-page: UNKNOWN
Author: Jhonnatha de Andrade Monteiro
Author-email: jhonnatha.am@gmail.com
License: MIT
Platform: UNKNOWN
